greetingTestFunction/__init__.py
greetingTestFunction/greetingTestFunction.py
greetingTestFunction-0.0.3.dist-info/METADATA
greetingTestFunction-0.0.3.dist-info/WHEEL
greetingTestFunction-0.0.3.dist-info/top_level.txt
greetingTestFunction-0.0.3.dist-info/RECORD
