Metadata-Version: 2.1
Name: greetingTestFunction
Version: 0.0.3
Summary: My first Python package
Author: rahulsingh
Author-email: rahulsingh336@gmail.com
Keywords: python,first package
Classifier: Development Status :: 3 - Alpha
Classifier: Intended Audience :: Education
Classifier: Programming Language :: Python :: 2
Classifier: Programming Language :: Python :: 3
Classifier: Operating System :: MacOS :: MacOS X
Classifier: Operating System :: Microsoft :: Windows
